dwdatareader/DWDataReaderLib.dll
dwdatareader/DWDataReaderLib.so
dwdatareader/DWDataReaderLib64.dll
dwdatareader/DWDataReaderLib64.so
dwdatareader/__init__.py
dwdatareader-1.2.0.dist-info/licenses/LICENSE
dwdatareader-1.2.0.dist-info/METADATA
dwdatareader-1.2.0.dist-info/WHEEL
dwdatareader-1.2.0.dist-info/top_level.txt
dwdatareader-1.2.0.dist-info/RECORD
