Metadata-Version: 2.4
Name: dwdatareader
Version: 1.2.0
Summary: Python module to interact with Dewesoft DWDataReaderLib shared library
Home-page: https://github.com/costerwi/dwdatareader/
Download-URL: https://github.com/costerwi/dwdatareader/tarball/master
Author: Carl Osterwisch
Author-email: costerwi@gmail.com
License: MIT
Classifier: Intended Audience :: Science/Research
Classifier: Topic :: Scientific/Engineering :: Information Analysis
Classifier: Programming Language :: Python :: 3
Classifier: Operating System :: Microsoft :: Windows
Classifier: Operating System :: POSIX :: Linux
Classifier: Development Status :: 4 - Beta
License-File: LICENSE
Dynamic: author
Dynamic: author-email
Dynamic: classifier
Dynamic: description
Dynamic: download-url
Dynamic: home-page
Dynamic: license
Dynamic: license-file
Dynamic: summary
